donphan/__init__.py
donphan/_column.py
donphan/_connection.py
donphan/_consts.py
donphan/_creatable.py
donphan/_custom_types.py
donphan/_enums.py
donphan/_insertable.py
donphan/_join.py
donphan/_object.py
donphan/_selectable.py
donphan/_sqltype.py
donphan/_table.py
donphan/_types.pyi
donphan/_view.py
donphan/py.typed
donphan/utils.py
donphan-4.11.1.dist-info/LICENSE
donphan-4.11.1.dist-info/METADATA
donphan-4.11.1.dist-info/WHEEL
donphan-4.11.1.dist-info/RECORD
